net_automation/__init__.py
net_automation/j2templates.py
net_automation/net_automation.py
net_automation/validators.py
net_automation/vyosbgp.template
network_automation_usman_u-0.1.23.dist-info/WHEEL
network_automation_usman_u-0.1.23.dist-info/METADATA
network_automation_usman_u-0.1.23.dist-info/LICENSE
network_automation_usman_u-0.1.23.dist-info/RECORD
