Metadata-Version: 2.1
Name: network-automation-usman-u
Version: 0.1.23
Summary: An ansible-like network automation framework.
Author: Usman
Author-email: usman@usman.network
Requires-Python: >=3.10,<4.0
Classifier: Programming Language :: Python :: 3
Classifier: Programming Language :: Python :: 3.10
Classifier: Programming Language :: Python :: 3.11
Requires-Dist: Jinja2 (>=3.1.2,<4.0.0)
Requires-Dist: discord-webhook (>=0.17.0,<0.18.0)
Requires-Dist: matplotlib (>=3.6.2,<4.0.0)
Requires-Dist: netmiko (>=4.1.2,<5.0.0)
Requires-Dist: pySMTP (>=1.1.0,<2.0.0)
Requires-Dist: requests (>=2.28.1,<3.0.0)
Requires-Dist: textfsm (==1.1.2)
